motor_driver/__init__.py
motor_driver/canmotorlib.py
mini_cheetah_motor_driver_socketcan-0.4.3.dist-info/LICENSE
mini_cheetah_motor_driver_socketcan-0.4.3.dist-info/METADATA
mini_cheetah_motor_driver_socketcan-0.4.3.dist-info/WHEEL
mini_cheetah_motor_driver_socketcan-0.4.3.dist-info/top_level.txt
mini_cheetah_motor_driver_socketcan-0.4.3.dist-info/RECORD
