Metadata-Version: 2.1
Name: mini-cheetah-motor-driver-socketcan
Version: 0.4.3
Summary: A Python Driver for MIT Mini-Cheetah Actuator which uses SocketCAN for communication.
Home-page: https://github.com/dfki-ric-underactuated-lab/mini-cheetah-tmotor-python-can
Author: Shubham Vyas
Author-email: Shubham.Vyas@dfki.de
Project-URL: Bug Tracker, https://github.com/dfki-ric-underactuated-lab/mini-cheetah-tmotor-python-can/issues
Classifier: Development Status :: 4 - Beta
Classifier: Programming Language :: Python :: 3.6
Classifier: License :: OSI Approved :: MIT License
Classifier: Operating System :: POSIX :: Linux
Classifier: Framework :: Robot Framework :: Tool
Classifier: Topic :: System :: Hardware :: Hardware Drivers
Requires-Python: >=3.6
License-File: LICENSE
Requires-Dist: bitstring
